openvino_genai/__init__.py
openvino_genai/__init__.pyi
openvino_genai/libopenvino_genai.2530.dylib
openvino_genai/py_openvino_genai.cpython-310-darwin.so
openvino_genai/py_openvino_genai.pyi
openvino_genai-2025.3.0.0.dist-info/LICENSE
openvino_genai-2025.3.0.0.dist-info/METADATA
openvino_genai-2025.3.0.0.dist-info/SECURITY.md
openvino_genai-2025.3.0.0.dist-info/WHEEL
openvino_genai-2025.3.0.0.dist-info/entry_points.txt
openvino_genai-2025.3.0.0.dist-info/third-party-programs.txt
openvino_genai-2025.3.0.0.dist-info/RECORD
